setup.py
elysia_dltools/__init__.py
elysia_dltools/logger.py
elysia_dltools/metric_cal.py
elysia_dltools.egg-info/PKG-INFO
elysia_dltools.egg-info/SOURCES.txt
elysia_dltools.egg-info/dependency_links.txt
elysia_dltools.egg-info/not-zip-safe
elysia_dltools.egg-info/top_level.txt