Metadata-Version: 2.1
Name: elysia-dltools
Version: 0.1.0
Summary: Elysia DeepLearning Tools
Home-page: UNKNOWN
Author: ElysiaAILab
Author-email: 3518925535@qq.com
License: UNKNOWN
Platform: UNKNOWN
